{
  "extends": "solhint:recommended",
  "rules": {
    "code-complexity": ["error", 11],
    "compiler-version": ["error", ">=0.8.23"],
    "func-name-mixedcase": "off",
    "func-visibility": ["error", { "ignoreConstructors": true }],
    "max-line-length": ["error", 121],
    "named-parameters-mapping": "warn",
    "no-console": "off",
    "not-rely-on-time": "off",
    "one-contract-per-file": "off",
    "no-empty-blocks": "off",
    "no-inline-assembly": "off",
    "avoid-tx-origin": "off",
    "quotes": "off"
  }
}
